{"OpenedDocuments":"[\"Process/Process Transaction.xaml\",\"Main.xaml\",\"Framework/GetTransactionData.xaml\"]","ProjectBreakpoints":"{\"Value\":{\"Process/Process Transaction.xaml\":[{\"ConditionalExpression\":null,\"ActionExpression\":null,\"ExpectedHitCounter\":null,\"ShouldContinueAfterAction\":false,\"IsTransient\":false,\"IsEnabled\":true,\"Id\":\"0138991e-71aa-4762-b522-d2b44916ee04\",\"ActivityIdRef\":\"SaveMailAttachments_1\",\"ActivityId\":\"1.304\",\"ActivityName\":\"Save Attachments\"},{\"ConditionalExpression\":null,\"ActionExpression\":null,\"ExpectedHitCounter\":null,\"ShouldContinueAfterAction\":false,\"IsTransient\":false,\"IsEnabled\":true,\"Id\":\"6f5b77f2-0224-4c97-9434-a2233a1e6cc9\",\"ActivityIdRef\":\"Flowchart_1\",\"ActivityId\":\"1.1\",\"ActivityName\":\"Flowchart\"},{\"ConditionalExpression\":null,\"ActionExpression\":null,\"ExpectedHitCounter\":null,\"ShouldContinueAfterAction\":false,\"IsTransient\":false,\"IsEnabled\":true,\"Id\":\"55b0ebf1-7f5d-47e3-aa60-9ae85c9fb9b6\",\"ActivityIdRef\":\"Sequence_25\",\"ActivityId\":\"1.71\",\"ActivityName\":\"Search Publiuc Register (Name First)\"}]}}","ProjectWatches":"{\"Value\":[]}"}